kiki_STT/setup.py
Kiki_STT-0.1.dist-info/METADATA
Kiki_STT-0.1.dist-info/WHEEL
Kiki_STT-0.1.dist-info/top_level.txt
Kiki_STT-0.1.dist-info/RECORD
