Metadata-Version: 2.1
Name: Kiki-STT
Version: 0.1
Summary: I am making a bot for trading community created by Muzamil
Author: Muzamil Kiki
Author-email: kingmuzamil156@gmail.com
